<?xml version="1.0" ?>
<SAMPLE_SET xmlns:xsi="http://www.w3.org/2001/XMLSchema-instance" xsi:noNamespaceSchemaLocation="ftp://ftp.sra.ebi.ac.uk/meta/xsd/sra_1_5/SRA.sample.xsd">
	<SAMPLE alias="585013a774d3e1009da14a21:sample:my_sample_1481642422_1" broker_name="TGAC" center_name="TGAC">
		<TITLE>585013a774d3e1009da14a21:sample:my_sample_1481642422_1</TITLE>
		<SAMPLE_NAME>
			<TAXON_ID>9685</TAXON_ID>
			<SCIENTIFIC_NAME>Felis catus</SCIENTIFIC_NAME>
		</SAMPLE_NAME>
		<SAMPLE_ATTRIBUTES>
			<SAMPLE_ATTRIBUTE>
				<TAG>Source Name</TAG>
				<VALUE>fluffy</VALUE>
			</SAMPLE_ATTRIBUTE>
			<SAMPLE_ATTRIBUTE>
				<TAG>cuteness</TAG>
				<VALUE>lots</VALUE>
			</SAMPLE_ATTRIBUTE>
			<SAMPLE_ATTRIBUTE>
				<TAG>age</TAG>
				<VALUE>5.0</VALUE>
				<UNITS>year</UNITS>
			</SAMPLE_ATTRIBUTE>
			<SAMPLE_ATTRIBUTE>
				<TAG>color</TAG>
				<VALUE>black</VALUE>
			</SAMPLE_ATTRIBUTE>
			<SAMPLE_ATTRIBUTE>
				<TAG>age</TAG>
				<VALUE>5.0</VALUE>
				<UNITS>year</UNITS>
			</SAMPLE_ATTRIBUTE>
		</SAMPLE_ATTRIBUTES>
	</SAMPLE>
</SAMPLE_SET>

